workspace_clients/__init__.py
workspace_clients/assets_client.py
workspace_clients/containers_client.py
workspace_clients/models.py
workspace_clients-3.0.0.dist-info/LICENSE.txt
workspace_clients-3.0.0.dist-info/METADATA
workspace_clients-3.0.0.dist-info/WHEEL
workspace_clients-3.0.0.dist-info/top_level.txt
workspace_clients-3.0.0.dist-info/RECORD
